{
  "posts": [
    {
      "name": "qqqqwwqcxq",
      "price": "qqqq",
      "color": "qqqqq",
      "id": 4
    },
    {
      "name": "[ww",
      "price": "[w",
      "color": "[",
      "pictures": [
        {
          "rawFile": {
            "path": "download.jpg"
          },
          "src": "blob:http://localhost:3000/6ad9ea8a-9124-4768-935e-0ce20f5b154d",
          "title": "download.jpg"
        }
      ],
      "id": 5
    },
    {
      "name": "rr",
      "price": "rr",
      "color": "r",
      "id": 6
    },
    {
      "name": "img",
      "price": "img",
      "color": "img",
      "pictures": [
        {
          "rawFile": {
            "path": "download.jpg"
          },
          "src": "blob:http://localhost:3000/f0df98bb-6c24-49c9-bc63-a3b709dcce7c",
          "title": "download.jpg"
        }
      ],
      "id": 7
    },
    {
      "name": "aa",
      "price": "aaa",
      "color": "aaa",
      "pictures": [
        {
          "rawFile": {
            "path": "download-1.png"
          },
          "src": "blob:http://localhost:3000/2d8ca91c-6c31-4de9-8dcb-eb92dad4fdb3",
          "title": "download-1.png"
        }
      ],
      "id": 8
    },
    {
      "price": "ee",
      "color": "e",
      "name": "eggggg",
      "pictures": [
        {
          "rawFile": {
            "path": "images.jpg"
          },
          "src": "blob:http://localhost:3000/cb620a04-1468-41fe-8698-582dda9ab39f",
          "title": "images.jpg"
        }
      ],
      "id": 9
    },
    {
      "name": "ttt",
      "price": "tt",
      "color": "tt",
      "pictures": [
        {
          "rawFile": {
            "path": "images-5.jpg"
          },
          "src": "blob:http://localhost:3000/bf556ea5-868b-4dfc-8a65-0c72baf70385",
          "title": "images-5.jpg"
        }
      ],
      "id": 10
    }
  ]
}